Metadata-Version: 2.1
Name: cogflow_lite
Version: 0.1.4
Summary: Lighter version of COG modules
Author: Sai_kireeti
Author-email: sai.kireeti@hiro-microdatacenters.nl
Classifier: Programming Language :: Python :: 3
Classifier: Operating System :: OS Independent
Requires-Python: >=3.10
License-File: LICENSE.md
Requires-Dist: mlflow==2.1.1
Requires-Dist: kfp==1.8.22
Requires-Dist: boto3
Requires-Dist: tenacity
Requires-Dist: pandas
Requires-Dist: numpy==1.24.4
Requires-Dist: kubernetes
Requires-Dist: minio
Requires-Dist: scikit-learn==1.2.0
Requires-Dist: awscli
Requires-Dist: s3fs
Requires-Dist: setuptools==68.2.2
Requires-Dist: kserve==0.12.0
Requires-Dist: ray==2.9.3
Requires-Dist: kafka-python==2.0.2
